aitg/__init__.py
aitg/gens/bart_summary_generator.py
aitg/gens/base.py
aitg/gens/classifier_generator.py
aitg/gens/embed_generator.py
aitg/gens/led_summary_generator.py
aitg/gens/qa_generator.py
aitg/gens/sfcodegen_generator.py
aitg/gens/sliding_generator.py
aitg/gens/t5_generator.py
aitg/gpt_cli.py
aitg/model.py
aitg/models/bart_classifier.py
aitg/models/bart_summarizer.py
aitg/models/gpt.py
aitg/models/led__summarizer.py
aitg/models/question_answer.py
aitg/models/sentence_embed.py
aitg/models/sfcodegen.py
aitg/models/t5.py
aitg/optimize.py
aitg/srv.py
aitg/t5_cli.py
aitg/util.py
aitg-3.4.0.dist-info/entry_points.txt
aitg-3.4.0.dist-info/WHEEL
aitg-3.4.0.dist-info/METADATA
aitg-3.4.0.dist-info/RECORD
